Kotti-2.0.0.dist-info/METADATA
Kotti-2.0.0.dist-info/RECORD
Kotti-2.0.0.dist-info/WHEEL
Kotti-2.0.0.dist-info/entry_points.txt
Kotti-2.0.0.dist-info/top_level.txt
kotti/__init__.py
kotti/events.py
kotti/fanstatic.py
kotti/filedepot.py
kotti/interfaces.py
kotti/message.py
kotti/migrate.py
kotti/populate.py
kotti/request.py
kotti/resources.py
kotti/sanitizers.py
kotti/security.py
kotti/sqla.py
kotti/testing.py
kotti/traversal.py
kotti/url_normalizer.py
kotti/util.py
kotti/workflow.py
kotti/workflow.zcml
kotti/alembic/env.py
kotti/alembic/script.py.mako
kotti/alembic/versions/1063d7178fa_add_node_path_column.py
kotti/alembic/versions/37a05f6246af_enlarge_name_title_path.py
kotti/alembic/versions/413fa5fcc581_add_filedepot.py
kotti/alembic/versions/4a3de0d0804a_add_foreignkey_indices.py
kotti/alembic/versions/559ce6eb0949_update_node_path_column.py
kotti/alembic/versions/57fecf5dbd62_initialize_workflow.py
kotti/alembic/versions/814c4ec72f1_add_file_columns_to_images_table.py
kotti/alembic/versions/9398ccf41c2_add_content_state_fo.py
kotti/locale/Kotti.pot
kotti/locale/cs/LC_MESSAGES/Kotti.mo
kotti/locale/cs/LC_MESSAGES/Kotti.po
kotti/locale/de/LC_MESSAGES/Kotti.mo
kotti/locale/de/LC_MESSAGES/Kotti.po
kotti/locale/en/LC_MESSAGES/Kotti.mo
kotti/locale/en/LC_MESSAGES/Kotti.po
kotti/locale/fr_FR/LC_MESSAGES/Kotti.mo
kotti/locale/fr_FR/LC_MESSAGES/Kotti.po
kotti/locale/it/LC_MESSAGES/Kotti.mo
kotti/locale/it/LC_MESSAGES/Kotti.po
kotti/locale/ja/LC_MESSAGES/Kotti.mo
kotti/locale/ja/LC_MESSAGES/Kotti.po
kotti/locale/ko/LC_MESSAGES/Kotti.mo
kotti/locale/ko/LC_MESSAGES/Kotti.po
kotti/locale/nl/LC_MESSAGES/Kotti.mo
kotti/locale/nl/LC_MESSAGES/Kotti.po
kotti/locale/pl/LC_MESSAGES/Kotti.mo
kotti/locale/pl/LC_MESSAGES/Kotti.po
kotti/locale/pt/LC_MESSAGES/Kotti.mo
kotti/locale/pt/LC_MESSAGES/Kotti.po
kotti/locale/sv/LC_MESSAGES/Kotti.mo
kotti/locale/sv/LC_MESSAGES/Kotti.po
kotti/static/base.css
kotti/static/base.min.css
kotti/static/contents.js
kotti/static/contents.min.js
kotti/static/edit.css
kotti/static/edit.min.css
kotti/static/favicon.ico
kotti/static/icon-transparent.png
