Metadata-Version: 2.1
Name: Kotti
Version: 2.0.0
Summary: A high-level, Pythonic web application framework based on Pyramid and SQLAlchemy.  It includes an extensible Content Management System called the Kotti CMS.
Home-page: http://kotti.pylonsproject.org/
Author: Kotti Developers
Author-email: kotti@googlegroups.com
License: BSD-derived (http://www.repoze.org/LICENSE.txt)
Keywords: kotti web cms wcms pylons pyramid sqlalchemy bootstrap
Platform: UNKNOWN
Classifier: Development Status :: 5 - Production/Stable
Classifier: Environment :: Web Environment
Classifier: Framework :: Pylons
Classifier: Framework :: Pyramid
Classifier: License :: Repoze Public License
Classifier: Natural Language :: Dutch
Classifier: Natural Language :: English
Classifier: Natural Language :: French
Classifier: Natural Language :: German
Classifier: Natural Language :: Italian
Classifier: Natural Language :: Japanese
Classifier: Natural Language :: Polish
Classifier: Natural Language :: Portuguese
Classifier: Natural Language :: Swedish
Classifier: Operating System :: POSIX
Classifier: Operating System :: Unix
Classifier: Programming Language :: Python
Classifier: Programming Language :: Python :: 3
Classifier: Programming Language :: Python :: 3 :: Only
Classifier: Programming Language :: Python :: 3.5
Classifier: Programming Language :: Python :: 3.6
Classifier: Programming Language :: Python :: Implementation
Classifier: Programming Language :: Python :: Implementation :: CPython
Classifier: Programming Language :: SQL
Classifier: Topic :: Internet
Classifier: Topic :: Internet :: WWW/HTTP
Classifier: Topic :: Internet :: WWW/HTTP :: Dynamic Content
Classifier: Topic :: Internet :: WWW/HTTP :: Dynamic Content :: CGI Tools/Libraries
Classifier: Topic :: Internet :: WWW/HTTP :: WSGI
Classifier: Topic :: Internet :: WWW/HTTP :: WSGI :: Application
Classifier: Topic :: Software Development
Classifier: Topic :: Software Development :: Libraries :: Application Frameworks
Provides-Extra: testing
Provides-Extra: development
Provides-Extra: docs
Requires-Dist: Babel
Requires-Dist: Chameleon (>=2.7.4)
Requires-Dist: alembic (>=0.8.0)
Requires-Dist: bleach (>=2.1.4)
Requires-Dist: bleach-whitelist
Requires-Dist: colander (>=1.3.2)
Requires-Dist: deform (>=2.0.5)
Requires-Dist: docopt
Requires-Dist: fanstatic (>=1.0.0)
Requires-Dist: filedepot
Requires-Dist: formencode (>=2.0.0a)
Requires-Dist: html2text
Requires-Dist: iso8601 (==0.1.11)
Requires-Dist: js.angular
Requires-Dist: js.bootstrap (>=3.0.0)
Requires-Dist: js.deform (>=2.0.3)
Requires-Dist: js.fineuploader
Requires-Dist: js.html5shiv
Requires-Dist: js.jquery (<2.0.0.dev)
Requires-Dist: js.jquery-form
Requires-Dist: js.jquery-tablednd
Requires-Dist: js.jquery-timepicker-addon
Requires-Dist: js.jqueryui (>=1.8.24)
Requires-Dist: js.jqueryui-tagit
Requires-Dist: lingua (>=1.3)
Requires-Dist: py-bcrypt
Requires-Dist: pyramid (>=1.9)
Requires-Dist: pyramid-beaker
Requires-Dist: pyramid-chameleon
Requires-Dist: pyramid-deform (>=0.2a3)
Requires-Dist: pyramid-mailer
Requires-Dist: pyramid-tm
Requires-Dist: pyramid-zcml (>=1.1.0)
Requires-Dist: repoze.lru
Requires-Dist: repoze.workflow (>=1.0b1)
Requires-Dist: repoze.zcml (>=1.0b1)
Requires-Dist: rfc6266-parser
Requires-Dist: sqlalchemy (>=1.0.0)
Requires-Dist: sqlalchemy-utils
Requires-Dist: transaction (>=1.1.0)
Requires-Dist: unidecode
Requires-Dist: usersettings
Requires-Dist: waitress
Requires-Dist: zope.deprecation
Requires-Dist: zope.interface
Requires-Dist: zope.sqlalchemy
Provides-Extra: development
Requires-Dist: check-manifest; extra == 'development'
Requires-Dist: pipdeptree; extra == 'development'
Requires-Dist: pyramid-debugtoolbar; extra == 'development'
Requires-Dist: kotti-tinymce (>=0.7.0); extra == 'development'
Provides-Extra: docs
Requires-Dist: Sphinx; extra == 'docs'
Requires-Dist: docutils; extra == 'docs'
Requires-Dist: repoze.sphinx.autointerface; extra == 'docs'
Requires-Dist: sphinx-rtd-theme; extra == 'docs'
Requires-Dist: setuptools-git; extra == 'docs'
Requires-Dist: pytest; extra == 'docs'
Provides-Extra: testing
Requires-Dist: WebTest; extra == 'testing'
Requires-Dist: mock; extra == 'testing'
Requires-Dist: Pillow; extra == 'testing'
Requires-Dist: py (>=1.4.29); extra == 'testing'
Requires-Dist: pyquery; extra == 'testing'
Requires-Dist: pytest (>=4.1.0); extra == 'testing'
Requires-Dist: pytest-cov; extra == 'testing'
Requires-Dist: pytest-pep8 (>=1.0.6); extra == 'testing'
Requires-Dist: pytest-travis-fold; extra == 'testing'
Requires-Dist: pytest-virtualenv; extra == 'testing'
Requires-Dist: pytest-xdist; extra == 'testing'
Requires-Dist: tox; extra == 'testing'
Requires-Dist: zope.testbrowser (>=5.0.0); extra == 'testing'
